[
    {
    "id": 1,
    "categoria": "Bouquets",
    "nombre": "Bouquet azul",
    "medida": "0.5 mts",
    "color": "azul",
    "precio": 5000,
    "precioFinal": 5500,
    "imagen": "bouquetAzul.webp",
    "descripcion": "Hermoso Bouquet azul"
    },
    {
    "id": 2,
    "categoria": "Pared",
    "nombre": "Pared azul",
    "medida": "2 mts",
    "color": "azul",
    "precio": 5000,
    "precioFinal": 5500,
    "imagen": "paredAzul.jpg",
    "descripcion": "Hermosa Pared azul"
    },
    {
    "id": 3,
    "categoria": "Guirnaldas",
    "nombre": "Guirnalda azul",
    "medida": "2 mtrs",
    "color": "azul",
    "precio": 5000,
    "precioFinal": 5500,
    "imagen": "guirnaldaAzul.jpg",
    "descripcion": "Hermosa Guirnalda azul"
    },
        {
    "id": 4,
    "categoria": "Bouquets",
    "nombre": "Bouquet rojo",
    "medida": "0.5 mts",
    "color": "rojo",
    "precio": 5000,
    "precioFinal": 5500,
    "imagen": "bouquetAzul.webp",
    "descripcion": "Hermoso Bouquet rojo"
    },
    {
    "id": 5,
    "categoria": "Pared",
    "nombre": "Pared rojo",
    "medida": "2 mts",
    "color": "rojo",
    "precio": 5000,
    "precioFinal": 5500,
    "imagen": "paredAzul.jpg",
    "descripcion": "Hermosa Pared rojo"
    },
    {
    "id": 6,
    "categoria": "Guirnaldas",
    "nombre": "Guirnalda rojo",
    "medida": "2 mtrs",
    "color": "rojo",
    "precio": 5000,
    "precioFinal": 5500,
    "imagen": "guirnaldaAzul.jpg",
    "descripcion": "Hermosa Guirnalda rojo"
    }
]
